{
  "boss_01": {
    "time": "15:53",
    "date": "2025-11-26",
    "modified": "2025-11-25T18:39:43.672091+00:00",
    "is_predicted": false
  },
  "boss_02": {
    "time": "04:38",
    "date": "2025-11-26",
    "modified": "2025-11-25T08:38:24.982802+00:00",
    "is_predicted": false
  },
  "boss_03": {
    "time": "09:31",
    "date": "2025-11-26",
    "modified": "2025-11-25T19:32:29.001221+00:00",
    "is_predicted": false
  },
  "boss_04": {
    "time": "04:41",
    "date": "2025-11-26",
    "modified": "2025-11-25T08:41:25.462783+00:00",
    "is_predicted": false
  },
  "boss_62c553e2": {
    "time": "18:41",
    "date": "2025-11-26",
    "modified": "2025-11-25T16:48:49.342857+00:00",
    "is_predicted": false
  },
  "boss_05": {
    "time": "04:11",
    "date": "2025-11-26",
    "modified": "2025-11-25T16:49:19.491053+00:00",
    "is_predicted": false
  },
  "boss_06": {
    "time": "09:14",
    "date": "2025-11-26",
    "modified": "2025-11-25T07:14:03.933405+00:00",
    "is_predicted": false
  },
  "boss_07": {
    "time": "11:45",
    "date": "2025-11-26",
    "modified": "2025-11-25T18:59:46.401688+00:00",
    "is_predicted": false
  },
  "boss_08": {
    "time": "07:31",
    "date": "2025-11-26",
    "modified": "2025-11-25T01:14:59.271635+00:00",
    "is_predicted": false
  },
  "boss_09": {
    "time": "03:25",
    "date": "2025-11-27",
    "modified": "2025-11-25T19:26:32.141503+00:00",
    "is_predicted": false
  },
  "boss_10": {
    "time": "03:21",
    "date": "2025-11-27",
    "modified": "2025-11-25T19:26:25.869873+00:00",
    "is_predicted": false
  },
  "boss_11": {
    "time": "07:59",
    "date": "2025-11-26",
    "modified": "2025-11-25T12:00:47.140528+00:00",
    "is_predicted": false
  },
  "boss_12": {
    "time": "19:05",
    "date": "2025-11-26",
    "modified": "2025-11-24T13:31:49.764995+00:00",
    "is_predicted": false
  },
  "boss_13": {
    "time": "09:19",
    "date": "2025-11-26",
    "modified": "2025-11-25T16:49:36.742631+00:00",
    "is_predicted": false
  },
  "boss_14": {
    "time": "14:34",
    "date": "2025-11-26",
    "modified": "2025-11-25T18:39:52.271942+00:00",
    "is_predicted": false
  },
  "boss_5d332052": {
    "time": "15:12",
    "date": "2025-11-26",
    "modified": "2025-11-25T19:13:27.691025+00:00",
    "is_predicted": false
  }
}