{
  "boss_01": {
    "time": "22:17",
    "date": "2026-01-21",
    "modified": "2026-01-21T00:48:41.659243+00:00",
    "is_predicted": false
  },
  "boss_02": {
    "time": "21:37",
    "date": "2026-01-21",
    "modified": "2026-01-21T05:15:56.321385+00:00",
    "is_predicted": false
  },
  "boss_03": {
    "time": "待確認",
    "date": "",
    "modified": "2026-01-21T04:31:59.026221+00:00",
    "is_predicted": false
  },
  "boss_04": {
    "time": "待確認",
    "date": "",
    "modified": "2026-01-21T04:31:59.026768+00:00",
    "is_predicted": false
  },
  "boss_62c553e2": {
    "time": "06:32",
    "date": "2026-01-22",
    "modified": "2026-01-21T04:32:02.609476+00:00",
    "is_predicted": false
  },
  "boss_05": {
    "time": "14:19",
    "date": "2026-01-21",
    "modified": "2026-01-21T00:23:50.390400+00:00",
    "is_predicted": false
  },
  "boss_06": {
    "time": "23:12",
    "date": "2026-01-21",
    "modified": "2026-01-20T21:12:41.842983+00:00",
    "is_predicted": false
  },
  "boss_07": {
    "time": "17:59",
    "date": "2026-01-21",
    "modified": "2026-01-21T01:01:34.499343+00:00",
    "is_predicted": false
  },
  "boss_08": {
    "time": "16:04",
    "date": "2026-01-21",
    "modified": "2026-01-20T08:04:24.325099+00:00",
    "is_predicted": false
  },
  "boss_09": {
    "time": "08:25",
    "date": "2026-01-22",
    "modified": "2026-01-21T00:26:45.573905+00:00",
    "is_predicted": false
  },
  "boss_10": {
    "time": "08:23",
    "date": "2026-01-22",
    "modified": "2026-01-21T00:23:58.668819+00:00",
    "is_predicted": false
  },
  "boss_11": {
    "time": "13:44",
    "date": "2026-01-21",
    "modified": "2026-01-20T18:00:36.466531+00:00",
    "is_predicted": false
  },
  "boss_12": {
    "time": "20:00",
    "date": "2026-01-21",
    "modified": "2026-01-19T12:36:09.106950+00:00",
    "is_predicted": false
  },
  "boss_13": {
    "time": "14:04",
    "date": "2026-01-21",
    "modified": "2026-01-20T18:04:58.123414+00:00",
    "is_predicted": false
  },
  "boss_14": {
    "time": "待確認",
    "date": "",
    "modified": "2026-01-21T04:31:59.028262+00:00",
    "is_predicted": false
  },
  "boss_5d332052": {
    "time": "待確認",
    "date": "",
    "modified": "2026-01-21T04:31:59.028418+00:00",
    "is_predicted": false
  }
}