{
  "boss_01": {
    "time": "00:36",
    "date": "2025-08-13",
    "modified": "2025-08-12T04:28:28.960526+00:00",
    "is_predicted": false
  },
  "boss_02": {
    "time": "17:40",
    "date": "2025-08-12",
    "modified": "2025-08-11T22:47:36.301063+00:00",
    "is_predicted": false
  },
  "boss_03": {
    "time": "18:14",
    "date": "2025-08-12",
    "modified": "2025-08-12T04:28:31.574775+00:00",
    "is_predicted": false
  },
  "boss_04": {
    "time": "17:46",
    "date": "2025-08-12",
    "modified": "2025-08-11T22:47:42.206186+00:00",
    "is_predicted": false
  },
  "boss_05": {
    "time": "18:11",
    "date": "2025-08-12",
    "modified": "2025-08-12T04:28:34.848118+00:00",
    "is_predicted": false
  },
  "boss_06": {
    "time": "22:20",
    "date": "2025-08-12",
    "modified": "2025-08-11T22:47:47.661852+00:00",
    "is_predicted": false
  },
  "boss_07": {
    "time": "20:06",
    "date": "2025-08-12",
    "modified": "2025-08-12T04:28:37.400857+00:00",
    "is_predicted": false
  },
  "boss_08": {
    "time": "17:10",
    "date": "2025-08-12",
    "modified": "2025-08-11T10:54:17.692009+00:00",
    "is_predicted": false
  },
  "boss_09": {
    "time": "17:12",
    "date": "2025-08-12",
    "modified": "2025-08-11T10:54:21.708080+00:00",
    "is_predicted": false
  },
  "boss_10": {
    "time": "17:14",
    "date": "2025-08-12",
    "modified": "2025-08-11T10:54:24.942836+00:00",
    "is_predicted": false
  },
  "boss_11": {
    "time": "17:44",
    "date": "2025-08-12",
    "modified": "2025-08-11T22:47:55.876129+00:00",
    "is_predicted": false
  },
  "boss_12": {
    "time": "17:14",
    "date": "2025-08-12",
    "modified": "2025-08-10T09:15:36.375025+00:00",
    "is_predicted": false
  },
  "boss_13": {
    "time": "18:51",
    "date": "2025-08-12",
    "modified": "2025-08-11T22:58:57.911682+00:00",
    "is_predicted": false
  },
  "boss_14": {
    "time": "23:18",
    "date": "2025-08-12",
    "modified": "2025-08-12T04:28:43.661617+00:00",
    "is_predicted": false
  },
  "boss_5d332052": {
    "time": "23:29",
    "date": "2025-08-12",
    "modified": "2025-08-12T04:28:46.635768+00:00",
    "is_predicted": false
  }
}