{
  "boss_01": {
    "time": "12:50",
    "date": "2025-11-25",
    "modified": "2025-11-24T15:20:39.619091+00:00",
    "is_predicted": false
  },
  "boss_02": {
    "time": "16:35",
    "date": "2025-11-25",
    "modified": "2025-11-24T20:36:47.369832+00:00",
    "is_predicted": false
  },
  "boss_03": {
    "time": "15:03",
    "date": "2025-11-25",
    "modified": "2025-11-25T01:15:20.876505+00:00",
    "is_predicted": false
  },
  "boss_04": {
    "time": "16:38",
    "date": "2025-11-25",
    "modified": "2025-11-24T20:38:55.843010+00:00",
    "is_predicted": false
  },
  "boss_62c553e2": {
    "time": "00:38",
    "date": "2025-11-26",
    "modified": "2025-11-24T22:39:01.025038+00:00",
    "is_predicted": false
  },
  "boss_05": {
    "time": "09:53",
    "date": "2025-11-25",
    "modified": "2025-11-24T19:54:52.764405+00:00",
    "is_predicted": false
  },
  "boss_06": {
    "time": "15:11",
    "date": "2025-11-25",
    "modified": "2025-11-24T13:31:29.749959+00:00",
    "is_predicted": false
  },
  "boss_07": {
    "time": "17:38",
    "date": "2025-11-25",
    "modified": "2025-11-25T01:15:43.594474+00:00",
    "is_predicted": false
  },
  "boss_08": {
    "time": "07:31",
    "date": "2025-11-26",
    "modified": "2025-11-25T01:14:59.271635+00:00",
    "is_predicted": false
  },
  "boss_09": {
    "time": "03:22",
    "date": "2025-11-26",
    "modified": "2025-11-24T19:42:59.239827+00:00",
    "is_predicted": false
  },
  "boss_10": {
    "time": "03:18",
    "date": "2025-11-26",
    "modified": "2025-11-24T19:43:13.663649+00:00",
    "is_predicted": false
  },
  "boss_11": {
    "time": "待確認",
    "date": "",
    "modified": "2025-11-25T01:12:17.707684+00:00",
    "is_predicted": false
  },
  "boss_12": {
    "time": "19:05",
    "date": "2025-11-26",
    "modified": "2025-11-24T13:31:49.764995+00:00",
    "is_predicted": false
  },
  "boss_13": {
    "time": "21:12",
    "date": "2025-11-25",
    "modified": "2025-11-25T01:14:03.932973+00:00",
    "is_predicted": false
  },
  "boss_14": {
    "time": "14:28",
    "date": "2025-11-25",
    "modified": "2025-11-24T19:43:27.433672+00:00",
    "is_predicted": false
  },
  "boss_5d332052": {
    "time": "15:02",
    "date": "2025-11-25",
    "modified": "2025-11-24T19:43:40.926511+00:00",
    "is_predicted": false
  }
}