{
  "boss_01": {
    "time": "02:27",
    "date": "2026-01-03",
    "modified": "2026-01-02T04:57:00.225516+00:00",
    "is_predicted": false
  },
  "boss_02": {
    "time": "07:59",
    "date": "2026-01-03",
    "modified": "2026-01-02T11:59:17.123105+00:00",
    "is_predicted": false
  },
  "boss_03": {
    "time": "01:33",
    "date": "2026-01-03",
    "modified": "2026-01-02T11:58:27.991369+00:00",
    "is_predicted": false
  },
  "boss_04": {
    "time": "08:00",
    "date": "2026-01-03",
    "modified": "2026-01-02T12:02:19.611182+00:00",
    "is_predicted": false
  },
  "boss_62c553e2": {
    "time": "09:39",
    "date": "2026-01-03",
    "modified": "2026-01-02T07:52:28.252510+00:00",
    "is_predicted": false
  },
  "boss_05": {
    "time": "01:31",
    "date": "2026-01-03",
    "modified": "2026-01-02T11:58:36.013095+00:00",
    "is_predicted": false
  },
  "boss_06": {
    "time": "01:34",
    "date": "2026-01-03",
    "modified": "2026-01-01T23:34:52.700642+00:00",
    "is_predicted": false
  },
  "boss_07": {
    "time": "07:07",
    "date": "2026-01-03",
    "modified": "2026-01-02T14:15:30.821614+00:00",
    "is_predicted": false
  },
  "boss_08": {
    "time": "10:02",
    "date": "2026-01-03",
    "modified": "2026-01-02T04:57:30.579402+00:00",
    "is_predicted": false
  },
  "boss_09": {
    "time": "07:36",
    "date": "2026-01-03",
    "modified": "2026-01-01T23:36:49.220010+00:00",
    "is_predicted": false
  },
  "boss_10": {
    "time": "07:33",
    "date": "2026-01-03",
    "modified": "2026-01-01T23:33:09.709523+00:00",
    "is_predicted": false
  },
  "boss_11": {
    "time": "12:49",
    "date": "2026-01-03",
    "modified": "2026-01-02T16:55:36.605844+00:00",
    "is_predicted": false
  },
  "boss_12": {
    "time": "19:45",
    "date": "2026-01-03",
    "modified": "2026-01-01T11:45:24.455882+00:00",
    "is_predicted": false
  },
  "boss_13": {
    "time": "待確認",
    "date": "",
    "modified": "2026-01-02T16:53:24.899855+00:00",
    "is_predicted": false
  },
  "boss_14": {
    "time": "07:23",
    "date": "2026-01-03",
    "modified": "2026-01-02T11:58:44.718922+00:00",
    "is_predicted": false
  },
  "boss_5d332052": {
    "time": "08:27",
    "date": "2026-01-03",
    "modified": "2026-01-02T12:33:03.159907+00:00",
    "is_predicted": false
  }
}