{
  "boss_01": {
    "time": "17:21",
    "date": "2025-09-15",
    "modified": "2025-09-15T03:31:09.948735+00:00",
    "is_predicted": false
  },
  "boss_02": {
    "time": "15:00",
    "date": "2025-09-15",
    "modified": "2025-09-14T19:35:42.613731+00:00",
    "is_predicted": false
  },
  "boss_03": {
    "time": "13:10",
    "date": "2025-09-15",
    "modified": "2025-09-15T03:31:12.615868+00:00",
    "is_predicted": false
  },
  "boss_04": {
    "time": "15:01",
    "date": "2025-09-15",
    "modified": "2025-09-14T19:35:46.435022+00:00",
    "is_predicted": false
  },
  "boss_05": {
    "time": "15:04",
    "date": "2025-09-15",
    "modified": "2025-09-15T03:31:16.772842+00:00",
    "is_predicted": false
  },
  "boss_06": {
    "time": "23:41",
    "date": "2025-09-15",
    "modified": "2025-09-15T03:31:19.842881+00:00",
    "is_predicted": false
  },
  "boss_07": {
    "time": "13:09",
    "date": "2025-09-15",
    "modified": "2025-09-15T03:31:22.875164+00:00",
    "is_predicted": false
  },
  "boss_08": {
    "time": "00:21",
    "date": "2025-09-16",
    "modified": "2025-09-14T19:35:53.893130+00:00",
    "is_predicted": false
  },
  "boss_09": {
    "time": "23:23",
    "date": "2025-09-15",
    "modified": "2025-09-14T19:35:55.975657+00:00",
    "is_predicted": false
  },
  "boss_10": {
    "time": "00:23",
    "date": "2025-09-16",
    "modified": "2025-09-14T19:35:58.111881+00:00",
    "is_predicted": false
  },
  "boss_11": {
    "time": "12:51",
    "date": "2025-09-15",
    "modified": "2025-09-14T19:36:00.697363+00:00",
    "is_predicted": false
  },
  "boss_12": {
    "time": "21:49",
    "date": "2025-09-15",
    "modified": "2025-09-13T23:45:58.479176+00:00",
    "is_predicted": false
  },
  "boss_13": {
    "time": "16:41",
    "date": "2025-09-15",
    "modified": "2025-09-14T20:42:34.011716+00:00",
    "is_predicted": true
  },
  "boss_14": {
    "time": "13:29",
    "date": "2025-09-15",
    "modified": "2025-09-14T19:36:05.920316+00:00",
    "is_predicted": false
  },
  "boss_5d332052": {
    "time": "14:42",
    "date": "2025-09-15",
    "modified": "2025-09-14T19:36:08.567007+00:00",
    "is_predicted": false
  }
}