{
  "boss_01": {
    "time": "02:35",
    "date": "2025-12-22",
    "modified": "2025-12-21T05:05:01.801666+00:00",
    "is_predicted": false
  },
  "boss_02": {
    "time": "07:19",
    "date": "2025-12-22",
    "modified": "2025-12-21T11:39:41.525725+00:00",
    "is_predicted": false
  },
  "boss_03": {
    "time": "00:52",
    "date": "2025-12-22",
    "modified": "2025-12-21T10:52:53.631187+00:00",
    "is_predicted": false
  },
  "boss_04": {
    "time": "07:20",
    "date": "2025-12-22",
    "modified": "2025-12-21T11:39:43.583944+00:00",
    "is_predicted": false
  },
  "boss_62c553e2": {
    "time": "08:16",
    "date": "2025-12-22",
    "modified": "2025-12-21T06:21:19.389603+00:00",
    "is_predicted": false
  },
  "boss_05": {
    "time": "23:20",
    "date": "2025-12-21",
    "modified": "2025-12-21T09:20:11.079570+00:00",
    "is_predicted": false
  },
  "boss_06": {
    "time": "00:49",
    "date": "2025-12-22",
    "modified": "2025-12-20T22:50:22.421894+00:00",
    "is_predicted": false
  },
  "boss_07": {
    "time": "04:29",
    "date": "2025-12-22",
    "modified": "2025-12-21T11:39:50.357288+00:00",
    "is_predicted": false
  },
  "boss_08": {
    "time": "09:00",
    "date": "2025-12-22",
    "modified": "2025-12-21T01:02:37.417631+00:00",
    "is_predicted": false
  },
  "boss_09": {
    "time": "06:44",
    "date": "2025-12-22",
    "modified": "2025-12-20T22:44:50.574861+00:00",
    "is_predicted": false
  },
  "boss_10": {
    "time": "06:35",
    "date": "2025-12-22",
    "modified": "2025-12-20T22:36:09.896590+00:00",
    "is_predicted": false
  },
  "boss_11": {
    "time": "00:23",
    "date": "2025-12-22",
    "modified": "2025-12-21T04:25:15.082844+00:00",
    "is_predicted": false
  },
  "boss_12": {
    "time": "19:32",
    "date": "2025-12-22",
    "modified": "2025-12-20T13:37:47.417600+00:00",
    "is_predicted": false
  },
  "boss_13": {
    "time": "00:16",
    "date": "2025-12-22",
    "modified": "2025-12-21T04:25:04.851259+00:00",
    "is_predicted": false
  },
  "boss_14": {
    "time": "05:53",
    "date": "2025-12-22",
    "modified": "2025-12-21T10:01:51.751608+00:00",
    "is_predicted": false
  },
  "boss_5d332052": {
    "time": "07:23",
    "date": "2025-12-22",
    "modified": "2025-12-21T11:40:00.757183+00:00",
    "is_predicted": false
  }
}